llama_index/packs/zenguard/__init__.py
llama_index/packs/zenguard/base.py
llama_index_packs_zenguard_guardrails-0.1.0.dist-info/METADATA
llama_index_packs_zenguard_guardrails-0.1.0.dist-info/WHEEL
llama_index_packs_zenguard_guardrails-0.1.0.dist-info/RECORD
