Metadata-Version: 2.1
Name: llama-index-packs-zenguard-guardrails
Version: 0.1.0
Summary: llama-index packs zenguard guardrails integration
License: MIT
Author: ZenGuard Team
Author-email: hello@zenguard.ai
Requires-Python: >=3.9,<4.0
Classifier: License :: OSI Approved :: MIT License
Classifier: Programming Language :: Python :: 3
Classifier: Programming Language :: Python :: 3.9
Classifier: Programming Language :: Python :: 3.10
Classifier: Programming Language :: Python :: 3.11
Requires-Dist: llama-index-core (>=0.10.0,<0.11.0)
Requires-Dist: zenguard (>=0.1.13,<0.2.0)
